shapleyrs-0.1.1.dist-info/METADATA
shapleyrs-0.1.1.dist-info/WHEEL
shapleyrs/__init__.py
shapleyrs/_shapley.abi3.so
shapleyrs/_shapley.pyi
shapleyrs/py.typed
shapleyrs-0.1.1.dist-info/RECORD
