Metadata-Version: 2.4
Name: shapleyrs
Version: 0.1.1
Classifier: Programming Language :: Rust
Classifier: Programming Language :: Python :: Implementation :: CPython
Classifier: Programming Language :: Python :: Implementation :: PyPy
Classifier: Development Status :: 3 - Alpha
Classifier: Intended Audience :: Developers
Classifier: Intended Audience :: Education
Classifier: Intended Audience :: Science/Research
Classifier: Operating System :: OS Independent
Classifier: Programming Language :: Python :: 3
Classifier: Programming Language :: Python :: 3.9
Classifier: Programming Language :: Python :: 3.10
Classifier: Programming Language :: Python :: 3.11
Classifier: Programming Language :: Python :: 3.12
Classifier: Programming Language :: Python :: 3.13
Requires-Dist: pytest ; extra == 'tests'
Provides-Extra: tests
Summary: A fast shapley score calculator
Keywords: GameTheory,Shapley
Author: Mathew Shen <datahonor@gmail.com>
Author-email: Mathew Shen <datahonor@gmail.com>
License: MIT
Requires-Python: >=3.9
Project-URL: Source Code, https://github.com/shenxiangzhuang/shapley
